zbuilder/__init__.py
zbuilder/cfg.py
zbuilder/cli.py
zbuilder/dns/__init__.py
zbuilder/dns/ansible.py
zbuilder/dns/aws.py
zbuilder/dns/azure.py
zbuilder/dns/bind.py
zbuilder/dns/do.py
zbuilder/dns/gcp.py
zbuilder/dns/powerdns.py
zbuilder/dns/vagrant.py
zbuilder/helpers.py
zbuilder/ipam/__init__.py
zbuilder/ipam/phpipam.py
zbuilder/options.py
zbuilder/vm/__init__.py
zbuilder/vm/aws.py
zbuilder/vm/azure.py
zbuilder/vm/do.py
zbuilder/vm/ganeti.py
zbuilder/vm/gcp.py
zbuilder/vm/proxmox.py
zbuilder/vm/vagrant.py
zbuilder/wrappers.py
zbuilder-0.0.67.dist-info/LICENSE
zbuilder-0.0.67.dist-info/METADATA
zbuilder-0.0.67.dist-info/WHEEL
zbuilder-0.0.67.dist-info/entry_points.txt
zbuilder-0.0.67.dist-info/RECORD
