Metadata-Version: 2.3
Name: zbuilder
Version: 0.0.67
Summary: Create VMs
License: GPL-3.0-or-later
Author: Chasiotis Nikos
Author-email: hasiotis@gmail.com
Requires-Python: >=3.11,<4
Classifier: Development Status :: 1 - Planning
Classifier: Environment :: Console
Classifier: Intended Audience :: System Administrators
Classifier: License :: OSI Approved :: GNU General Public License v3 or later (GPLv3+)
Classifier: Operating System :: OS Independent
Classifier: Programming Language :: Python
Classifier: Programming Language :: Python :: 3
Classifier: Programming Language :: Python :: 3.11
Classifier: Programming Language :: Python :: 3.12
Classifier: Programming Language :: Python :: 3.13
Classifier: Programming Language :: Python :: 3.6
Classifier: Programming Language :: Python :: 3.7
Classifier: Programming Language :: Python :: 3.8
Classifier: Programming Language :: Python :: Implementation :: PyPy
Requires-Dist: Jinja2 (>=3.0,<4.0)
Requires-Dist: PyJWT (>=2.5.0,<3.0.0)
Requires-Dist: ansible (>=11.9.0,<12.0.0)
Requires-Dist: arrow (>=1.1,<2.0)
Requires-Dist: azure-mgmt-compute (>=21.0,<22.0)
Requires-Dist: azure-mgmt-dns (>=8.0,<9.0)
Requires-Dist: azure-mgmt-network (>=19.0,<20.0)
Requires-Dist: azure-mgmt-resource (>=18.0,<19.0)
Requires-Dist: boto3 (>=1.17,<2.0)
Requires-Dist: click (>=8,<9)
Requires-Dist: colorama (>=0.4,<0.5)
Requires-Dist: delegator.py (>=0.1.1,<0.2.0)
Requires-Dist: dnspython (>=2,<3)
Requires-Dist: dpath (>=2.0,<3.0)
Requires-Dist: google-api-python-client (>=2.9,<3.0)
Requires-Dist: google-auth-oauthlib (>=0.4,<0.5)
Requires-Dist: google-cloud-dns (>=0.32,<0.33)
Requires-Dist: massedit (>=0.70.0,<0.71.0)
Requires-Dist: msrestazure (>=0.6.4,<0.7.0)
Requires-Dist: oauthlib (>=3.2.1,<4.0.0)
Requires-Dist: proxmoxer (>=1.1,<2.0)
Requires-Dist: python-digitalocean (>=1.16,<2.0)
Requires-Dist: requests (>=2,<3)
Requires-Dist: retrying (>=1.3,<2.0)
Requires-Dist: ruamel.yaml (>=0.17,<0.18)
Requires-Dist: setuptools (>=80.9.0,<81.0.0)
Requires-Dist: tabulate (>=0.8,<0.9)
Project-URL: Repository, https://github.com/hasiotis/zbuilder
